LICENSE
README.md
setup.py
vuno/__init__.py
vuno/__main__.py
vuno/buffer.py
vuno/commands.py
vuno/config.py
vuno/editor.py
vuno/keybindings.py
vuno/ui.py
vuno.egg-info/PKG-INFO
vuno.egg-info/SOURCES.txt
vuno.egg-info/dependency_links.txt
vuno.egg-info/entry_points.txt
vuno.egg-info/requires.txt
vuno.egg-info/top_level.txt